Workbook

Sheet 数据映射说明
B1: TikTok Shop 经营利润核算表 - 数据映射说明
B3: ⚠️ 币种说明
B4: 结算数据（收入/平台费/广告/物流等） | C4: 币种: THB（泰铢） | D4: 来源: 结算明细、订单明细、推广数据、佣金数据、售后数据
B5: 商品成本 | C5: 币种: CNY（人民币）→ 需换算为 THB | D5: 换算方式: 成本价(CNY) ÷ 汇率(THB/CNY) 或 成本价(CNY) × 汇率(CNY/THB)
B6: 其他费用（7店铺成本美妆） | C6: 币种: CNY（人民币）→ 需换算为 THB | D6: 来源: 7店铺成本美妆.xlsx
B8: 【数据源 → 模板字段 映射关系】
B9: 模板字段 | C9: 数据来源 | D9: 取数逻辑
B11: ── 收入端 ──
B12: GMV | C12: 结算明细 [享受折扣前小计] | D12: 按SKU求和
B13: 有效销售额 | C13: 结算明细 [享受商家折扣后小计] | D13: 按SKU求和：折扣后小计 - 退款小计
B14: 退款金额 | C14: 结算明细 [享受商家折扣后的退款小计] | D14: 按SKU求和（取绝对值）
B15: 卖家折扣 | C15: 结算明细 [商家折扣] | D15: 按SKU求和（取绝对值）
B16: 净销售收入 | C16: 计算 | D16: 有效销售额 - 卖家折扣
B17: 买家付运费 | C17: 结算明细 [买家支付运费] | D17: 按SKU求和
B19: ── 成本端（THB部分）──
B20: 平台佣金 | C20: 结算明细 [TikTok Shop 佣金费] | D20: 按SKU求和（取绝对值）
B21: 交易手续费 | C21: 结算明细 [交易手续费] | D21: 按SKU求和（取绝对值）
B22: 平台税费及其他 | C22: 结算明细 [电商增长服务费+基础设施费+其他] | D22: 按SKU求和
B23: 推广费用 | C23: 结算明细 [GMV Max 广告费] | D23: 按SKU求和（取绝对值）
B24: 达人佣金 | C24: 结算明细 [联盟佣金] | D24: 按SKU求和（取绝对值）
B25: 尾程物流 | C25: 结算明细 [商家运费] | D25: 按SKU求和（取绝对值）
B26: 售后损失 | C26: 售后退款明细 + 结算明细退款 | D26: 按SKU统计
B28: ── 成本端（CNY→THB换算）──
B29: 商品成本(CNY) | C29: 泰国商品资料 [成本价（含头程物流版）] | D29: 按SKU匹配：Seller SKU → 商品编码 → 成本价(CNY)
B30: 商品成本(THB) | C30: 计算 | D30: 商品成本(CNY) × 汇率 → 换算为THB后填入利润明细
B31: 其他费用(CNY) | C31: 7店铺成本美妆 | D31: 杂项费用汇总
B32: 其他费用(THB) | C32: 计算 | D32: 其他费用(CNY) × 汇率 → 换算为THB后填入
B34: ── 关键匹配链路 ──
B35: SKU关联 | D35: 结算明细[已售商品详情] → 提取SKU ID → 订单明细[SKU ID] → 获取Seller SKU → 商品资料[商品编码] → 获取成本价(CNY)
B36: 汇率换算 | D36: ⚠️ 成本价(CNY) 需 ÷ 汇率转为THB，填入利润明细表
B37: 广告关联 | C37: 商品级推广数据 | D37: 按广告组名称匹配到SKU（需人工建立映射）

Sheet 01-经营总览
A1: TikTok Shop 经营利润总览
A2: 统计周期: | B2: 2026年7月 | C2: 结算币种: | D2: THB | E2: 汇率(CNY→THB): | F2: 约5.0 | G2: ⚠️成本为CNY需换算 | H2: 见数据映射说明
A4: 📈 核心经营指标
A5: GMV总额 | C5: 有效销售额 | E5: 净销售收入 | G5: 经营贡献利润
A6: =SUM(利润明细!F:F) | C6: =SUM(利润明细!G:G) | E6: =SUM(利润明细!I:I) | G6: =SUM(利润明细!X:X)
A7: 订单量 | C7: 销量(件) | E7: 经营利润率 | G7: 总变动成本率
A8: =SUM(利润明细!D:D) | C8: =SUM(利润明细!E:E) | E8: =IFERROR(SUM(利润明细!X:X)/SUM(利润明细!G:G),0) | G8: =IFERROR(SUM(利润明细!W:W)/SUM(利润明细!G:G),0)
A9: 💰 收入结构（THB）
A10: 项目 | B10: 金额(THB) | C10: 占有效销售额比 | D10: 说明
A11: GMV总额 | B11: =SUM(利润明细!F:F) | C11: =IFERROR(B11/SUM(利润明细!G:G),0) | D11: 享受折扣前小计
A12: 减：退款 | B12: =SUM(利润明细!H:H) | C12: =IFERROR(B12/SUM(利润明细!G:G),0) | D12: 退款小计
A13: 有效销售额 | B13: =SUM(利润明细!G:G) | C13: =IFERROR(B13/SUM(利润明细!G:G),0) | D13: GMV - 退款
A14: 减：卖家折扣 | B14: =SUM(利润明细!J:J) | C14: =IFERROR(B14/SUM(利润明细!G:G),0) | D14: 商家折扣
A15: 净销售收入 | B15: =SUM(利润明细!I:I) | C15: =IFERROR(B15/SUM(利润明细!G:G),0) | D15: 有效销售 - 折扣
A17: 💸 成本费用结构（THB，商品成本已从CNY换算）
A18: 成本项目 | B18: 金额(THB) | C18: 占有效销售额比 | D18: 说明
A19: 商品成本(CNY→THB) | B19: =SUM(利润明细!L:L) | C19: =IFERROR(B19/SUM(利润明细!G:G),0) | D19: 成本价(CNY)×汇率，含头程物流
A20: 平台佣金 | B20: =SUM(利润明细!N:N) | C20: =IFERROR(B20/SUM(利润明细!G:G),0)
A21: 交易手续费 | B21: =SUM(利润明细!O:O) | C21: =IFERROR(B21/SUM(利润明细!G:G),0)
A22: 平台税费及其他 | B22: =SUM(利润明细!P:P) | C22: =IFERROR(B22/SUM(利润明细!G:G),0) | D22: 电商增长+基础设施+其他
A23: 推广费用 | B23: =SUM(利润明细!Q:Q) | C23: =IFERROR(B23/SUM(利润明细!G:G),0) | D23: GMV Max广告费
A24: 达人佣金 | B24: =SUM(利润明细!R:R) | C24: =IFERROR(B24/SUM(利润明细!G:G),0) | D24: 联盟佣金
A25: 尾程物流 | B25: =SUM(利润明细!S:S) | C25: =IFERROR(B25/SUM(利润明细!G:G),0) | D25: 商家运费
A26: 售后损失 | B26: =SUM(利润明细!U:U) | C26: =IFERROR(B26/SUM(利润明细!G:G),0)
A27: 其他费用(CNY→THB) | B27: =SUM(利润明细!V:V) | C27: =IFERROR(B27/SUM(利润明细!G:G),0) | D27: 杂项(CNY)×汇率
A28: 总变动成本 | B28: =SUM(利润明细!W:W) | C28: =IFERROR(B28/SUM(利润明细!G:G),0) | D28: 以上所有变动成本之和
A30: 📊 利润计算（THB）
A31: 净销售收入 | B31: =SUM(利润明细!I:I)
A32: 减：商品成本 | B32: =SUM(利润明细!L:L)
A33: 毛利润 | B33: =SUM(利润明细!I:I)-SUM(利润明细!L:L)
A34: 毛利率 | B34: =IFERROR((SUM(利润明细!I:I)-SUM(利润明细!L:L))/SUM(利润明细!G:G),0)
A35: 减：总变动成本 | B35: =SUM(利润明细!W:W)
A36: 经营贡献利润 | B36: =SUM(利润明细!X:X)
A37: 经营贡献利润率 | B37: =IFERROR(SUM(利润明细!X:X)/SUM(利润明细!G:G),0)

Sheet 02-利润明细
A1: TikTok Shop 利润明细表（SKU维度，全部THB）
A2: 基础信息 | D2: 销售数据 | G2: 收入计算 | L2: 成本&毛利 | N2: 平台费用 | Q2: 推广&达人 | S2: 物流&其他 | V2: 利润指标
A3: 序号 | B3: Seller SKU | C3: 商品名称 | D3: 订单量 | E3: 销量(件) | F3: GMV | G3: 有效销售额 | H3: 退款金额 | I3: 净销售收入 | J3: 卖家折扣 | K3: 买家付运费 | L3: 商品成本(THB) | M3: 毛利率 | N3: 平台佣金 | O3: 交易手续费 | P3: 平台税费及其他 | Q3: 推广费用 | R3: 达人佣金 | S3: 尾程物流 | T3: 其他费用 | U3: 售后损失 | V3: 总变动成本 | W3: 经营贡献利润 | X3: 经营利润率
A4: 1 | I4: =IFERROR(G4-J4,0) | M4: =IFERROR((G4-L4)/G4,0) | V4: =IFERROR(L4+N4+O4+P4+Q4+R4+S4+T4+U4,0) | W4: =IFERROR(I4-W4,0) | X4: =IFERROR(X4/G4,0)
A5: 2 | I5: =IFERROR(G5-J5,0) | M5: =IFERROR((G5-L5)/G5,0) | V5: =IFERROR(L5+N5+O5+P5+Q5+R5+S5+T5+U5,0) | W5: =IFERROR(I5-W5,0) | X5: =IFERROR(X5/G5,0)
A6: 3 | I6: =IFERROR(G6-J6,0) | M6: =IFERROR((G6-L6)/G6,0) | V6: =IFERROR(L6+N6+O6+P6+Q6+R6+S6+T6+U6,0) | W6: =IFERROR(I6-W6,0) | X6: =IFERROR(X6/G6,0)
A7: 4 | I7: =IFERROR(G7-J7,0) | M7: =IFERROR((G7-L7)/G7,0) | V7: =IFERROR(L7+N7+O7+P7+Q7+R7+S7+T7+U7,0) | W7: =IFERROR(I7-W7,0) | X7: =IFERROR(X7/G7,0)
A8: 5 | I8: =IFERROR(G8-J8,0) | M8: =IFERROR((G8-L8)/G8,0) | V8: =IFERROR(L8+N8+O8+P8+Q8+R8+S8+T8+U8,0) | W8: =IFERROR(I8-W8,0) | X8: =IFERROR(X8/G8,0)
A9: 6 | I9: =IFERROR(G9-J9,0) | M9: =IFERROR((G9-L9)/G9,0) | V9: =IFERROR(L9+N9+O9+P9+Q9+R9+S9+T9+U9,0) | W9: =IFERROR(I9-W9,0) | X9: =IFERROR(X9/G9,0)
A10: 7 | I10: =IFERROR(G10-J10,0) | M10: =IFERROR((G10-L10)/G10,0) | V10: =IFERROR(L10+N10+O10+P10+Q10+R10+S10+T10+U10,0) | W10: =IFERROR(I10-W10,0) | X10: =IFERROR(X10/G10,0)
A11: 8 | I11: =IFERROR(G11-J11,0) | M11: =IFERROR((G11-L11)/G11,0) | V11: =IFERROR(L11+N11+O11+P11+Q11+R11+S11+T11+U11,0) | W11: =IFERROR(I11-W11,0) | X11: =IFERROR(X11/G11,0)
A12: 9 | I12: =IFERROR(G12-J12,0) | M12: =IFERROR((G12-L12)/G12,0) | V12: =IFERROR(L12+N12+O12+P12+Q12+R12+S12+T12+U12,0) | W12: =IFERROR(I12-W12,0) | X12: =IFERROR(X12/G12,0)
A13: 10 | I13: =IFERROR(G13-J13,0) | M13: =IFERROR((G13-L13)/G13,0) | V13: =IFERROR(L13+N13+O13+P13+Q13+R13+S13+T13+U13,0) | W13: =IFERROR(I13-W13,0) | X13: =IFERROR(X13/G13,0)
A14: 11 | I14: =IFERROR(G14-J14,0) | M14: =IFERROR((G14-L14)/G14,0) | V14: =IFERROR(L14+N14+O14+P14+Q14+R14+S14+T14+U14,0) | W14: =IFERROR(I14-W14,0) | X14: =IFERROR(X14/G14,0)
A15: 12 | I15: =IFERROR(G15-J15,0) | M15: =IFERROR((G15-L15)/G15,0) | V15: =IFERROR(L15+N15+O15+P15+Q15+R15+S15+T15+U15,0) | W15: =IFERROR(I15-W15,0) | X15: =IFERROR(X15/G15,0)
... A103: 100 | I103: =IFERROR(G103-J103,0) | M103: =IFERROR((G103-L103)/G103,0) | V103: =IFERROR(L103+N103+O103+P103+Q103+R103+S103+T103+U103,0) | W103: =IFERROR(I103-W103,0) | X103: =IFERROR(X103/G103,0)
A104: 合计 | D104: =SUM(D4:D102) | E104: =SUM(E4:E102) | F104: =SUM(F4:F102) | G104: =SUM(G4:G102) | H104: =SUM(H4:H102) | I104: =SUM(I4:I102) | J104: =SUM(J4:J102) | K104: =SUM(K4:K102) | L104: =SUM(L4:L102) | M104: =IFERROR((G104-L104)/G104,0) | N104: =SUM(N4:N102) | O104: =SUM(O4:O102) | P104: =SUM(P4:P102) | Q104: =SUM(Q4:Q102) | R104: =SUM(R4:R102) | S104: =SUM(S4:S102) | T104: =SUM(T4:T102) | U104: =SUM(U4:U102) | V104: =SUM(W4:W102) | W104: =SUM(X4:X102) | X104: =IFERROR(X104/G104,0)

Sheet 03-成本结构
A1: 成本结构与费用占比（全部THB）
A2: 成本项目 | B2: 金额(THB) | C2: 占有效销售额比 | D2: 说明
B3: 商品成本(CNY→THB) | C3: =SUM(利润明细!L:L) | D3: =IFERROR(C3/SUM(利润明细!G:G),0) | E3: 成本价(CNY)×汇率，含头程物流
B4: 平台佣金 | C4: =SUM(利润明细!N:N) | D4: =IFERROR(C4/SUM(利润明细!G:G),0) | E4: TikTok Shop佣金
B5: 交易手续费 | C5: =SUM(利润明细!O:O) | D5: =IFERROR(C5/SUM(利润明细!G:G),0) | E5: 支付通道费
B6: 平台税费及其他 | C6: =SUM(利润明细!P:P) | D6: =IFERROR(C6/SUM(利润明细!G:G),0) | E6: 电商增长+基础设施+其他
B7: 推广费用 | C7: =SUM(利润明细!Q:Q) | D7: =IFERROR(C7/SUM(利润明细!G:G),0) | E7: GMV Max广告费
B8: 达人佣金 | C8: =SUM(利润明细!R:R) | D8: =IFERROR(C8/SUM(利润明细!G:G),0) | E8: 联盟佣金
B9: 尾程物流 | C9: =SUM(利润明细!S:S) | D9: =IFERROR(C9/SUM(利润明细!G:G),0) | E9: 商家运费
B10: 售后损失 | C10: =SUM(利润明细!U:U) | D10: =IFERROR(C10/SUM(利润明细!G:G),0) | E10: 退款中商家承担
B11: 其他费用(CNY→THB) | C11: =SUM(利润明细!V:V) | D11: =IFERROR(C11/SUM(利润明细!G:G),0) | E11: 杂项(CNY)×汇率
B12: 总变动成本 | C12: =SUM(C3:C11) | D12: =IFERROR(C12/SUM(利润明细!G:G),0)

Sheet 04-推广分析
A1: 推广效果分析（THB）
A2: 广告组名称 | B2: 消耗(Cost) | C2: 净消耗(Net Cost) | D2: SKU订单数 | E2: 单均成本 | F2: 总收入(Gross Rev) | G2: ROI | H2: 说明
B63: 合计 | C63: =SUM(C3:C62) | D63: =SUM(D3:D62) | E63: =SUM(E3:E62) | F63: =SUM(F3:F62) | G63: =IFERROR(F63/C63,0)

Sheet 05-达人分析
A1: 达人渠道分析（THB）
A2: 商品ID | B2: 商品名称 | C2: GMV | D2: 成交件数 | E2: 预计佣金 | F2: 销售达人 | G2: 佣金率 | H2: 已退款GMV

Sheet 06-售后分析
A1: 售后损失分析
A2: 项目 | B2: 金额/数量 | C2: 比率 | D2: 说明
B3: 退货退款订单数 | C3: 39 | E3: Return and refund
B4: 仅退款订单数 | C4: 11 | E4: Refund only
B5: 售后总订单数 | C5: 50
B6: 退款总额 | E6: 从结算明细统计
B7: 售后率(按金额) | D7: 退款÷GMV
B8: 售后损失(商家承担) | C8: =SUM(利润明细!U:U)
B9: 售后损失率 | D9: 售后损失÷有效销售额

Sheet 07-指标定义
A1: 指标定义与计算公式
A2: 指标 | B2: 计算公式/定义 | C2: 数据来源
B3: GMV | C3: 享受折扣前小计(结算明细) 按SKU求和 | D3: 结算明细
B4: 有效销售额 | C4: 享受商家折扣后小计 - 退款小计 | D4: 结算明细
B5: 净销售收入 | C5: 有效销售额 - 商家折扣 | D5: 结算明细
B6: 商品成本(CNY) | C6: 成本价(含头程) × 销量 | D6: 商品资料表
B7: 商品成本(THB) | C7: 商品成本(CNY) × 汇率 | D7: 计算
B8: 毛利润 | C8: 净销售收入 - 商品成本(THB) | D8: 计算
B9: 毛利率 | C9: 毛利润 ÷ 有效销售额 | D9: 计算
B10: 平台佣金 | C10: TikTok Shop 佣金费 按SKU求和 | D10: 结算明细
B11: 交易手续费 | C11: 交易手续费 按SKU求和 | D11: 结算明细
B12: 平台税费及其他 | C12: 电商增长+基础设施+其他平台费 | D12: 结算明细
B13: 推广费用 | C13: GMV Max 广告费 按SKU求和 | D13: 结算明细
B14: 达人佣金 | C14: 联盟佣金 按SKU求和 | D14: 结算明细
... B19: ROI | C19: 有效销售额 ÷ (商品成本+推广费用) | D19: 计算
B21: 📌 重要口径说明
B22: ⚠️ 结算数据(收入/平台费/广告/佣金/物流) = THB（泰铢）
B23: ⚠️ 商品成本(商品资料表) = CNY（人民币），需用汇率换算为THB后填入
B24: ⚠️ 其他费用(7店铺成本美妆) = CNY（人民币），需用汇率换算为THB
B25: 所有"率"类指标，分母统一为「有效销售额」
B26: GMV只做参考，不用于利润率计算
B27: 平台费用以结算明细实际扣款为准，不用理论费率
B28: 固定成本(人工/房租等)暂不计入经营利润
B29: 头程物流已包含在商品成本中
B30: 结算明细中金额为负 = 平台扣款，处理时取绝对值
